{"id":"114","titel":"Starke Kita","beschreibung":"Dieser Online-Selbstlernkurs ist speziell für Leitungskräfte von Kindertageseinrichtungen und Fachkräfte konzipiert und bietet eine praxisnahe Weiterbildung. Ziel ist es, die Kernaufgaben oder Schwerpunkte dieser Berufsgruppen optimal zu gestalten und neues Wissen direkt im Kita-Alltag anzuwenden. Eine starke Leitung und kompetente Fachkräfte sind dabei entscheidend für eine gute Zusammenarbeit in der Kita. Der Kurs ist komplett online und kann jederzeit begonnen werden.","url":"https://www.oncampus.de/starke_kita_mooc","format":["Online-Kurs"],"thema":["Personalmanagement/-entwicklung"],"author":"Deutsche Kinder- und Jugendstiftung","altersgruppe":["0-3 Jahre","3-6 Jahre"],"erscheinungsjahr":"","herausgeber":"Deutsche Kinder- und Jugendstiftung"}