{
  "id": "14",
  "titel": "\"Was ist Adultismus?\"",
  "beschreibung": "Von Adultismus sprechen wir, wenn ein älterer Mensch einen jüngeren nicht ernst nimmt, benachteiligt oder unterdrückt. Daher ist es für Mitarbeiter:innen in Einrichtungen der Frühen Bildung wichtig, sensibel für dieses Thema zu sein. Der kostenlose Online-Kurs zum Thema Adultismus eignet sich sehr gut, um in das Thema einzusteigen. Mit Teilnahmezertifikat.",
  "url": "https://www.indipaed.de/courses/adultismus",
  "format": ["Online-Kurs"],
  "thema": ["Pädagogische Beziehungen"],
  "author": "InDiPaed - Institut für Digitale Pädagogik",
  "altersgruppe": ["0-3 Jahre", "3-6 Jahre", "6-10 Jahre"],
  "erscheinungsjahr": "",
  "herausgeber": "InDiPaed - Institut für Digitale Pädagogik"
}
