{"id":"20","titel":"Partizipation in der Kita. Praxistipps zur Beteiligung von Kindern im Alltag","beschreibung":"Das Dokument bietet praxisnahe Tipps und Empfehlungen für Erzieherinnen und Erzieher, wie sie die Partizipation von Kindern in der Kita fördern und unterstützen können. Dabei geht es um die Beteiligung der Kinder an Entscheidungen und Planungen, um ihre Meinungen und Ideen sowie um die Förderung ihrer Selbstständigkeit und Eigenverantwortung.","url":"https://www.vielfalt-mediathek.de/wp-content/uploads/2021/06/Haus-Neuland_Partizipation_in_der_Kita-Praxistipps_zur_Beteiligung_von_Kindern_im_Alter_Vielfalt-Mediathek.pdf","format":["Praxisimpuls"],"thema":["Partizipation und Demokratie"],"author":"Haus Neuland e.V.","altersgruppe":["0-3 Jahre","3-6 Jahre"],"erscheinungsjahr":"","herausgeber":"Haus Neuland e.V."}