{"id":"64","titel":"Kinder vor Rassismus schützen","beschreibung":"Der Power Me Podcast #02 befasst sich mit dem Thema \"Kinder vor Rassismus schützen\". Die Gastgeberin Nuran Serin spricht mit Maryam Haschemi Yekani über ihre Beratungsarbeit und wie sie Kinder vor Diskriminierung schützen kann. Es werden Beispielfälle und Hürden bei der Beratung von Kindern aufgezeigt sowie Chancen für eine bessere Unterstützung der Kinder und Zusammenarbeit der beteiligten Instanzen besprochen.","link":"https://www.powermeberlin.de/podcasts/episode/59b733d7/power-me-podcast-02-maryam-haschemi-yekani-kinder-vor-rassismus-schutzen","format":["Podcast"],"thema":["Inklusion und Diversität"],"author":"Nuran Serin","altersgruppe":["0-3 Jahre","3-6 Jahre","6-10 Jahre"],"erscheinungsjahr":"2022","herausgeber":"Ariba e.V."}